{
    "deletedOn": "13_February_2026_1601",
    "showData": {
        "showID": 102,
        "showName": "Descendant of the Sun",
        "otherNames": [],
        "showImage": null,
        "watchStartedOn": "10-02-2023",
        "watchEndedOn": "11-02-2023",
        "releasedYear": 2016,
        "releaseDate": null,
        "totalEpisodes": 16,
        "showType": "Drama",
        "nativeLanguage": "Korean",
        "watchedLanguage": "Korean",
        "country": "South Korea",
        "comments": "Not Bad. One Time Watchable",
        "ratings": 6,
        "genres": [
            "Army",
            "Medical",
            "Romance"
        ],
        "network": [
            "KBS2"
        ],
        "againWatchedDates": [
            "24-03-2025"
        ],
        "updatedOn": "13 February 2026",
        "updatedDetails": "First Time Uploaded",
        "synopsis": null,
        "topRatings": 1200,
        "Duration": null,
        "director": [],
        "tags": [],
        "cast": [],
        "extendedCastInfo": {},
        "sitePriorityUsed": {
            "showImage": null,
            "releaseDate": null,
            "otherNames": null,
            "Duration": null,
            "synopsis": null,
            "director": null,
            "tags": null,
            "cast": null
        }
    }
}