{
    "scriptVersion": "v10.5",
    "runID": "RUN_20260319_165334",
    "timestamp": "19 March 2026 04:53 PM (IST)",
    "backupType": "partial_diff",
    "showID": 103,
    "showName": "Love At First Hate",
    "releasedYear": 2018,
    "updatedDetails": "Watch Started On, Watch Ended On, Category, Again Watched Dates Updated",
    "changedFields": {
        "watchStartedOn": {
            "old": "02-06-2023",
            "new": "06-02-2023"
        },
        "watchEndedOn": {
            "old": "02-06-2023",
            "new": "06-02-2023"
        },
        "genres": {
            "old": [
                "Celebrity",
                "Comedy",
                "Romance"
            ],
            "new": [
                "Romance",
                "Comedy",
                "Celebrity"
            ]
        },
        "againWatchedDates": {
            "old": [
                "23-02-2024",
                "12-08-2025"
            ],
            "new": [
                "23-02-2024",
                "08-12-2025"
            ]
        }
    }
}