{
    "scriptVersion": "v12.1.2",
    "runID": "RUN_20260407_213217",
    "timestamp": "07 April 2026 09:34 PM (IST)",
    "showID": 402,
    "showName": "Female CEO Love Me",
    "fetchedFields": {
        "releaseDate": {
            "value": "March 28, 2022",
            "source": "mydramalist",
            "source_link": "https://mydramalist.com/692383-female-ceo-fall-in-love-with-me/episode/1"
        }
    },
    "sitePriorityUsed": {
        "showImage": null,
        "releaseDate": "mydramalist",
        "otherNames": null,
        "Duration": null,
        "synopsis": null,
        "director": null,
        "tags": null,
        "cast": null,
        "network": null,
        "airedOn": null
    }
}