{
    "scriptVersion": "v12.1.2",
    "runID": "RUN_20260606_142319",
    "timestamp": "06 June 2026 02:23 PM (IST)",
    "showID": 412,
    "showName": "Business Marriage",
    "fetchedFields": {
        "showImage": {
            "value": "412.jpg",
            "source": "asianwiki (Fallback: mydramalist)"
        },
        "releaseDate": {
            "value": "May 24, 2024 - Jul 19, 2024",
            "source": "mydramalist"
        },
        "otherNames": {
            "value": [
                "Bijinesu Kon: Suki ni Nattara Rikonshimasu",
                "Business Marriage: If We Fall in Love",
                "We'll Divorce",
                "Business Marriage: If You Fall in Love",
                "You Will Divorce",
                "Business Kon: Suki ni Nattara Rikonshimasu"
            ],
            "source": "mydramalist"
        },
        "Duration": {
            "value": "24 mins",
            "source": "mydramalist"
        },
        "synopsis": {
            "value": "After being dumped by her ex-boyfriend on their six-year anniversary, Sayama Miyabi immerses herself into her job on the sales team at a real estate firm. Meanwhile, Donose Tsukasa, a highly successful company CEO, seeks a marriage of convenience to satisfy societal expectations.\n\nWhen he meets Miyabi, he proposes a “business marriage” where she can live rent-free in a luxury apartment, and he can present a “wife\" to the world. There’s just\n\none clause: If they develop genuine romantic emotions, they must divorce. However, cupid has other plans, and their arrangement begins to falter as emotions come into play.",
            "source": "asianwiki (Fallback: mydramalist)"
        },
        "director": {
            "value": [
                "Tanazawa Takayoshi"
            ],
            "source": "mydramalist"
        },
        "tags": {
            "value": [
                "Expressed Consent",
                "Saleswoman Female Lead",
                "Company President (CEO) Male Lead",
                "Miniseries",
                "Marriage Of Convenience",
                "Adapted From A Manga"
            ],
            "source": "mydramalist"
        },
        "cast": {
            "value": {
                "Main Role": 2,
                "Support Role": 3,
                "Guest Role": 1,
                "Director": 1
            },
            "source": "mydramalist"
        },
        "network": {
            "value": [
                "MBS",
                "TVK"
            ],
            "source": "mydramalist"
        },
        "airedOn": {
            "value": [
                "Friday"
            ],
            "source": "mydramalist"
        }
    },
    "sitePriorityUsed": {
        "showImage": "asianwiki (Fallback: mydramalist)",
        "releaseDate": "mydramalist",
        "otherNames": "mydramalist",
        "Duration": "mydramalist",
        "synopsis": "asianwiki (Fallback: mydramalist)",
        "director": "mydramalist",
        "tags": "mydramalist",
        "cast": "mydramalist",
        "network": "mydramalist",
        "airedOn": "mydramalist"
    }
}