{
  "scriptVersion": "v2.4.3 (Final)",
  "showID": 102,
  "showName": "Tale of the Nine Tailed",
  "language": "korean",
  "timestamp": "26 October 2025 12:17 AM (IST)",
  "fetchedFields": {
    "showImage": {
      "value": "https://brucebanner001.github.io/my-movie-database/images/102.jpg",
      "source": "mydramalist"
    },
    "releaseDate": {
      "value": "7 october 2020 - 3 december 2020",
      "source": "mydramalist"
    },
    "otherNames": {
      "value": [
        "Chasing the Nine-Tailed Fox",
        "Gumihodyeon",
        "Le conte des neuf queues",
        "O Conto da Raposa de Nove Caudas",
        "Tale of Gumiho",
        "Tale of the Nine Tailed",
        "Tale of the Nine-Tailed Season 1",
        "The Story of Gumiho",
        "The Tale of the Nine-Tailed Fox",
        "Сказание о Кумихо",
        "حكاية الثعلب ذو الذيول التسعة"
      ],
      "source": "mydramalist"
    },
    "Duration": {
      "value": 10,
      "source": "mydramalist"
    },
    "synopsis": {
      "value": "Tale of the Nine-Tailed (Korean Drama); 구미호뎐; Chasing the Nine-Tailed Fox;Gumihodyeon;Le conte des neuf queues;O Conto da Raposa de Nove Caudas;Tale of (Source: MyDramaList)",
      "source": "mydramalist"
    }
  },
  "sitePriorityUsed": {
    "image": "mydramalist",
    "releaseDate": "mydramalist",
    "otherNames": "mydramalist",
    "duration": "mydramalist",
    "synopsis": "mydramalist"
  }
}