{
    "scriptVersion": "v12.1.2",
    "runID": "RUN_20260407_203633",
    "timestamp": "07 April 2026 08:46 PM (IST)",
    "showID": 1435,
    "showName": "I Order You",
    "fetchedFields": {
        "showImage": {
            "value": "1435.jpg",
            "source": "asianwiki (Fallback: mydramalist)",
            "source_link": "https://mydramalist.com/14062-i-order-you/articles"
        }
    },
    "sitePriorityUsed": {
        "showImage": "asianwiki (Fallback: mydramalist)",
        "releaseDate": null,
        "otherNames": null,
        "Duration": null,
        "synopsis": null,
        "director": null,
        "tags": null,
        "cast": null,
        "network": null,
        "airedOn": null
    }
}