{
    "scriptVersion": "v3.0",
    "runID": "RUN_20251121_161549",
    "timestamp": "21 November 2025 04:16 PM (IST)",
    "showID": 3008,
    "showName": "Island Season 1",
    "fetchedFields": {
        "releaseDate": {
            "value": null,
            "source": "asianwiki"
        },
        "otherNames": {
            "value": [],
            "source": "mydramalist"
        },
        "duration": {
            "value": null,
            "source": "mydramalist"
        },
        "synopsis": {
            "value": null,
            "source": "asianwiki"
        },
        "image": {
            "value": null,
            "source": "asianwiki"
        }
    }
}